{
  "generator-jhipster": {
    "promptValues": {
      "packageName": "com.motic",
      "nativeLanguage": "zh-cn"
    },
    "jhipsterVersion": "5.4.2",
    "applicationType": "microservice",
    "baseName": "service",
    "packageName": "com.motic",
    "packageFolder": "com/motic",
    "serverPort": "8082",
    "authenticationType": "uaa",
    "uaaBaseName": "uaa",
    "cacheProvider": "hazelcast",
    "enableHibernateCache": true,
    "websocket": false,
    "databaseType": "sql",
    "devDatabaseType": "mssql",
    "prodDatabaseType": "mssql",
    "searchEngine": false,
    "messageBroker": false,
    "serviceDiscoveryType": "eureka",
    "buildTool": "maven",
    "enableSwaggerCodegen": false,
    "jwtSecretKey": "ZWVkYjkxMTM5OTRhYjVhNWE1Y2M2NmY2MjEzZDMxNDRiODk2OGI5NWI3NDM4M2Q0OWYxZWZmMTAxMDczZWYwOTZhN2RmYzZiNTM2MWQzMDU5NDAyMTlkYjczN2YwYmY0ZDI0NTI1OGRjNmI4MTgyNTlhMzY1MjkzYmM2M2E5NDc=",
    "enableTranslation": true,
    "languages": [
      "zh-cn",
      "en"
    ],
    "testFrameworks": [],
    "jhiPrefix": "jhi",
    "clientPackageManager": "npm",
    "nativeLanguage": "zh-cn",
    "skipClient": true,
    "skipUserManagement": true
  }
}