{
    "fluentMethods": true,
    "clientRootFolder": "service1",
    "relationships": [
        {
            "relationshipName": "manager",
            "otherEntityName": "employee",
            "relationshipType": "many-to-one",
            "otherEntityField": "lastName"
        },
        {
            "relationshipName": "department",
            "otherEntityName": "department",
            "relationshipType": "many-to-one",
            "relationshipValidateRules": [
                "required"
            ],
            "otherEntityField": "departmentName"
        }
    ],
    "fields": [
        {
            "fieldName": "firstName",
            "fieldType": "String",
            "fieldValidateRules": [
                "required"
            ]
        },
        {
            "fieldName": "lastName",
            "fieldType": "String"
        },
        {
            "fieldName": "email",
            "fieldType": "String"
        },
        {
            "fieldName": "phoneNumber",
            "fieldType": "String"
        },
        {
            "fieldName": "hireDate",
            "fieldType": "Instant"
        },
        {
            "fieldName": "salary",
            "fieldType": "Long"
        }
    ],
    "changelogDate": "20181027144531",
    "dto": "no",
    "searchEngine": false,
    "service": "no",
    "entityTableName": "employee",
    "jpaMetamodelFiltering": false,
    "pagination": "no",
    "microserviceName": "service1"
}
